pytest_stubprocess.py
pytest_stubprocess-0.1.0.dist-info/METADATA
pytest_stubprocess-0.1.0.dist-info/RECORD
pytest_stubprocess-0.1.0.dist-info/WHEEL
pytest_stubprocess-0.1.0.dist-info/entry_points.txt
pytest_stubprocess-0.1.0.dist-info/top_level.txt
