Metadata-Version: 2.1
Name: pytest-stubprocess
Version: 0.1.0
Summary: Provide stub implementations for subprocesses in Python tests
Home-page: https://github.com/aptbosox/pytest-stubprocess
Author: Alex Thompson
Author-email: aptbosox@gmail.com
Maintainer: Alex Thompson
Maintainer-email: aptbosox@gmail.com
License: MIT
Platform: UNKNOWN
Classifier: Development Status :: 3 - Alpha
Classifier: Framework :: Pytest
Classifier: Intended Audience :: Developers
Classifier: Topic :: Software Development :: Testing
Classifier: Programming Language :: Python
Classifier: Programming Language :: Python :: 3
Classifier: Programming Language :: Python :: 3.6
Classifier: Programming Language :: Python :: 3.7
Classifier: Programming Language :: Python :: Implementation :: CPython
Classifier: Operating System :: POSIX
Classifier: License :: OSI Approved :: MIT License
Requires-Python: >=3.6
Requires-Dist: attrs
Requires-Dist: pytest (>=3.5.0)
Requires-Dist: pytest-mock
